{
  "hash": "093a36e1",
  "configHash": "1e5b460b",
  "lockfileHash": "e3b0c442",
  "browserHash": "0b8270d0",
  "optimized": {
    "vite-plugin-node-polyfills/shims/buffer": {
      "src": "../../node_modules/.deno/vite-plugin-node-polyfills@0.22.0/node_modules/vite-plugin-node-polyfills/shims/buffer/dist/index.js",
      "file": "vite-plugin-node-polyfills_shims_buffer.js",
      "fileHash": "e7be6721",
      "needsInterop": false
    },
    "vite-plugin-node-polyfills/shims/global": {
      "src": "../../node_modules/.deno/vite-plugin-node-polyfills@0.22.0/node_modules/vite-plugin-node-polyfills/shims/global/dist/index.js",
      "file": "vite-plugin-node-polyfills_shims_global.js",
      "fileHash": "d4dc3293",
      "needsInterop": false
    },
    "vite-plugin-node-polyfills/shims/process": {
      "src": "../../node_modules/.deno/vite-plugin-node-polyfills@0.22.0/node_modules/vite-plugin-node-polyfills/shims/process/dist/index.js",
      "file": "vite-plugin-node-polyfills_shims_process.js",
      "fileHash": "045025cf",
      "needsInterop": false
    },
    "vue": {
      "src": "../../node_modules/.deno/vue@3.5.13/node_modules/vue/dist/vue.runtime.esm-bundler.js",
      "file": "vue.js",
      "fileHash": "938ab262",
      "needsInterop": false
    },
    "easyqrcodejs": {
      "src": "../../node_modules/.deno/easyqrcodejs@4.5.1/node_modules/easyqrcodejs/dist/easy.qrcode.min.js",
      "file": "easyqrcodejs.js",
      "fileHash": "4f092b77",
      "needsInterop": true
    },
    "@fortawesome/vue-fontawesome": {
      "src": "../../node_modules/.deno/@fortawesome+vue-fontawesome@3.0.8/node_modules/@fortawesome/vue-fontawesome/index.es.js",
      "file": "@fortawesome_vue-fontawesome.js",
      "fileHash": "40428a69",
      "needsInterop": false
    },
    "@fortawesome/fontawesome-svg-core": {
      "src": "../../node_modules/.deno/@fortawesome+fontawesome-svg-core@6.7.2/node_modules/@fortawesome/fontawesome-svg-core/index.mjs",
      "file": "@fortawesome_fontawesome-svg-core.js",
      "fileHash": "5ff317f8",
      "needsInterop": false
    },
    "@fortawesome/free-brands-svg-icons": {
      "src": "../../node_modules/.deno/@fortawesome+free-brands-svg-icons@6.7.2/node_modules/@fortawesome/free-brands-svg-icons/index.mjs",
      "file": "@fortawesome_free-brands-svg-icons.js",
      "fileHash": "cb26d242",
      "needsInterop": false
    },
    "@fortawesome/free-solid-svg-icons": {
      "src": "../../node_modules/.deno/@fortawesome+free-solid-svg-icons@6.7.2/node_modules/@fortawesome/free-solid-svg-icons/index.mjs",
      "file": "@fortawesome_free-solid-svg-icons.js",
      "fileHash": "67b0087b",
      "needsInterop": false
    },
    "primevue/config": {
      "src": "../../node_modules/.deno/primevue@4.2.5/node_modules/primevue/config/index.mjs",
      "file": "primevue_config.js",
      "fileHash": "e8291a5d",
      "needsInterop": false
    },
    "primevue/button": {
      "src": "../../node_modules/.deno/primevue@4.2.5/node_modules/primevue/button/index.mjs",
      "file": "primevue_button.js",
      "fileHash": "1177517e",
      "needsInterop": false
    },
    "primevue/divider": {
      "src": "../../node_modules/.deno/primevue@4.2.5/node_modules/primevue/divider/index.mjs",
      "file": "primevue_divider.js",
      "fileHash": "2b22a501",
      "needsInterop": false
    },
    "@primevue/themes/aura": {
      "src": "../../node_modules/.deno/@primevue+themes@4.2.5/node_modules/@primevue/themes/aura/index.mjs",
      "file": "@primevue_themes_aura.js",
      "fileHash": "f6b09541",
      "needsInterop": false
    }
  },
  "chunks": {
    "chunk-WBTY6NSQ": {
      "file": "chunk-WBTY6NSQ.js"
    },
    "chunk-7IJ65XYU": {
      "file": "chunk-7IJ65XYU.js"
    },
    "chunk-32NSYED4": {
      "file": "chunk-32NSYED4.js"
    },
    "chunk-4GWX6YWG": {
      "file": "chunk-4GWX6YWG.js"
    },
    "chunk-HUP34BGO": {
      "file": "chunk-HUP34BGO.js"
    },
    "chunk-T2TQJYUV": {
      "file": "chunk-T2TQJYUV.js"
    }
  }
}